[
  {
    "publisher": "Springer Science and Business Media LLC",
    "issue": "3",
    "DOI": "10.1007/s004420050035",
    "type": "article-journal",
    "page": "297-305",
    "source": "Crossref",
    "title": "Linking biodiversity to ecosystem function: implications for conservation ecology",
    "volume": "122",
    "author": [
      {
        "given": "M. W.",
        "family": "Schwartz"
      },
      {
        "given": "C. A.",
        "family": "Brigham"
      },
      {
        "given": "J. D.",
        "family": "Hoeksema"
      },
      {
        "given": "K. G.",
        "family": "Lyons"
      },
      {
        "given": "M. H.",
        "family": "Mills"
      },
      {
        "given": "P.J.",
        "family": "van Mantgem"
      }
    ],
    "container-title": "Oecologia",
    "issued": {
      "date-parts": [
        [
          2000,
          2,
          23
        ]
      ]
    },
    "URL": "https://doi.org/cjwdg4",
    "container-title-short": "Oecologia",
    "PMID": "28308280",
    "id": "qiGjxMrN",
    "note": "This CSL Item was generated by Manubot v0.5.2 from its persistent identifier (standard_id).\nstandard_id: doi:10.1007/s004420050035"
  },
  {
    "publisher": "American Chemical Society (ACS)",
    "issue": "6",
    "DOI": "10.1021/acs.analchem.5b04804",
    "type": "article-journal",
    "page": "3317-3323",
    "source": "Crossref",
    "title": "Integration of Molecular Networking and <i>In-Silico</i> MS/MS Fragmentation for Natural Products Dereplication",
    "volume": "88",
    "author": [
      {
        "given": "Pierre-Marie",
        "family": "Allard"
      },
      {
        "given": "Tiphaine",
        "family": "Péresse"
      },
      {
        "given": "Jonathan",
        "family": "Bisson"
      },
      {
        "given": "Katia",
        "family": "Gindro"
      },
      {
        "given": "Laurence",
        "family": "Marcourt"
      },
      {
        "given": "Van Cuong",
        "family": "Pham"
      },
      {
        "given": "Fanny",
        "family": "Roussi"
      },
      {
        "given": "Marc",
        "family": "Litaudon"
      },
      {
        "given": "Jean-Luc",
        "family": "Wolfender"
      }
    ],
    "container-title": "Analytical Chemistry",
    "language": "en",
    "issued": {
      "date-parts": [
        [
          2016,
          3,
          1
        ]
      ]
    },
    "URL": "https://doi.org/f8v86w",
    "container-title-short": "Anal. Chem.",
    "PMID": "26882108",
    "id": "Y25XY9UD",
    "note": "This CSL Item was generated by Manubot v0.5.2 from its persistent identifier (standard_id).\nstandard_id: doi:10.1021/acs.analchem.5b04804"
  },
  {
    "publisher": "Springer Science and Business Media LLC",
    "issue": "8",
    "DOI": "10.1038/nbt.3597",
    "type": "article-journal",
    "page": "828-837",
    "source": "Crossref",
    "title": "Sharing and community curation of mass spectrometry data with Global Natural Products Social Molecular Networking",
    "volume": "34",
    "author": [
      {
        "given": "Mingxun",
        "family": "Wang"
      },
      {
        "given": "Jeremy J",
        "family": "Carver"
      },
      {
        "given": "Vanessa V",
        "family": "Phelan"
      },
      {
        "given": "Laura M",
        "family": "Sanchez"
      },
      {
        "given": "Neha",
        "family": "Garg"
      },
      {
        "given": "Yao",
        "family": "Peng"
      },
      {
        "given": "Don Duy",
        "family": "Nguyen"
      },
      {
        "given": "Jeramie",
        "family": "Watrous"
      },
      {
        "given": "Clifford A",
        "family": "Kapono"
      },
      {
        "given": "Tal",
        "family": "Luzzatto-Knaan"
      },
      {
        "given": "Carla",
        "family": "Porto"
      },
      {
        "given": "Amina",
        "family": "Bouslimani"
      },
      {
        "given": "Alexey V",
        "family": "Melnik"
      },
      {
        "given": "Michael J",
        "family": "Meehan"
      },
      {
        "given": "Wei-Ting",
        "family": "Liu"
      },
      {
        "given": "Max",
        "family": "Crüsemann"
      },
      {
        "given": "Paul D",
        "family": "Boudreau"
      },
      {
        "given": "Eduardo",
        "family": "Esquenazi"
      },
      {
        "given": "Mario",
        "family": "Sandoval-Calderón"
      },
      {
        "given": "Roland D",
        "family": "Kersten"
      },
      {
        "given": "Laura A",
        "family": "Pace"
      },
      {
        "given": "Robert A",
        "family": "Quinn"
      },
      {
        "given": "Katherine R",
        "family": "Duncan"
      },
      {
        "given": "Cheng-Chih",
        "family": "Hsu"
      },
      {
        "given": "Dimitrios J",
        "family": "Floros"
      },
      {
        "given": "Ronnie G",
        "family": "Gavilan"
      },
      {
        "given": "Karin",
        "family": "Kleigrewe"
      },
      {
        "given": "Trent",
        "family": "Northen"
      },
      {
        "given": "Rachel J",
        "family": "Dutton"
      },
      {
        "given": "Delphine",
        "family": "Parrot"
      },
      {
        "given": "Erin E",
        "family": "Carlson"
      },
      {
        "given": "Bertrand",
        "family": "Aigle"
      },
      {
        "given": "Charlotte F",
        "family": "Michelsen"
      },
      {
        "given": "Lars",
        "family": "Jelsbak"
      },
      {
        "given": "Christian",
        "family": "Sohlenkamp"
      },
      {
        "given": "Pavel",
        "family": "Pevzner"
      },
      {
        "given": "Anna",
        "family": "Edlund"
      },
      {
        "given": "Jeffrey",
        "family": "McLean"
      },
      {
        "given": "Jörn",
        "family": "Piel"
      },
      {
        "given": "Brian T",
        "family": "Murphy"
      },
      {
        "given": "Lena",
        "family": "Gerwick"
      },
      {
        "given": "Chih-Chuang",
        "family": "Liaw"
      },
      {
        "given": "Yu-Liang",
        "family": "Yang"
      },
      {
        "given": "Hans-Ulrich",
        "family": "Humpf"
      },
      {
        "given": "Maria",
        "family": "Maansson"
      },
      {
        "given": "Robert A",
        "family": "Keyzers"
      },
      {
        "given": "Amy C",
        "family": "Sims"
      },
      {
        "given": "Andrew R",
        "family": "Johnson"
      },
      {
        "given": "Ashley M",
        "family": "Sidebottom"
      },
      {
        "given": "Brian E",
        "family": "Sedio"
      },
      {
        "given": "Andreas",
        "family": "Klitgaard"
      },
      {
        "given": "Charles B",
        "family": "Larson"
      },
      {
        "given": "Cristopher A",
        "family": "Boya P"
      },
      {
        "given": "Daniel",
        "family": "Torres-Mendoza"
      },
      {
        "given": "David J",
        "family": "Gonzalez"
      },
      {
        "given": "Denise B",
        "family": "Silva"
      },
      {
        "given": "Lucas M",
        "family": "Marques"
      },
      {
        "given": "Daniel P",
        "family": "Demarque"
      },
      {
        "given": "Egle",
        "family": "Pociute"
      },
      {
        "given": "Ellis C",
        "family": "O'Neill"
      },
      {
        "given": "Enora",
        "family": "Briand"
      },
      {
        "given": "Eric J N",
        "family": "Helfrich"
      },
      {
        "given": "Eve A",
        "family": "Granatosky"
      },
      {
        "given": "Evgenia",
        "family": "Glukhov"
      },
      {
        "given": "Florian",
        "family": "Ryffel"
      },
      {
        "given": "Hailey",
        "family": "Houson"
      },
      {
        "given": "Hosein",
        "family": "Mohimani"
      },
      {
        "given": "Jenan J",
        "family": "Kharbush"
      },
      {
        "given": "Yi",
        "family": "Zeng"
      },
      {
        "given": "Julia A",
        "family": "Vorholt"
      },
      {
        "given": "Kenji L",
        "family": "Kurita"
      },
      {
        "given": "Pep",
        "family": "Charusanti"
      },
      {
        "given": "Kerry L",
        "family": "McPhail"
      },
      {
        "given": "Kristian Fog",
        "family": "Nielsen"
      },
      {
        "given": "Lisa",
        "family": "Vuong"
      },
      {
        "given": "Maryam",
        "family": "Elfeki"
      },
      {
        "given": "Matthew F",
        "family": "Traxler"
      },
      {
        "given": "Niclas",
        "family": "Engene"
      },
      {
        "given": "Nobuhiro",
        "family": "Koyama"
      },
      {
        "given": "Oliver B",
        "family": "Vining"
      },
      {
        "given": "Ralph",
        "family": "Baric"
      },
      {
        "given": "Ricardo R",
        "family": "Silva"
      },
      {
        "given": "Samantha J",
        "family": "Mascuch"
      },
      {
        "given": "Sophie",
        "family": "Tomasi"
      },
      {
        "given": "Stefan",
        "family": "Jenkins"
      },
      {
        "given": "Venkat",
        "family": "Macherla"
      },
      {
        "given": "Thomas",
        "family": "Hoffman"
      },
      {
        "given": "Vinayak",
        "family": "Agarwal"
      },
      {
        "given": "Philip G",
        "family": "Williams"
      },
      {
        "given": "Jingqui",
        "family": "Dai"
      },
      {
        "given": "Ram",
        "family": "Neupane"
      },
      {
        "given": "Joshua",
        "family": "Gurr"
      },
      {
        "given": "Andrés M C",
        "family": "Rodríguez"
      },
      {
        "given": "Anne",
        "family": "Lamsa"
      },
      {
        "given": "Chen",
        "family": "Zhang"
      },
      {
        "given": "Kathleen",
        "family": "Dorrestein"
      },
      {
        "given": "Brendan M",
        "family": "Duggan"
      },
      {
        "given": "Jehad",
        "family": "Almaliti"
      },
      {
        "given": "Pierre-Marie",
        "family": "Allard"
      },
      {
        "given": "Prasad",
        "family": "Phapale"
      },
      {
        "given": "Louis-Felix",
        "family": "Nothias"
      },
      {
        "given": "Theodore",
        "family": "Alexandrov"
      },
      {
        "given": "Marc",
        "family": "Litaudon"
      },
      {
        "given": "Jean-Luc",
        "family": "Wolfender"
      },
      {
        "given": "Jennifer E",
        "family": "Kyle"
      },
      {
        "given": "Thomas O",
        "family": "Metz"
      },
      {
        "given": "Tyler",
        "family": "Peryea"
      },
      {
        "given": "Dac-Trung",
        "family": "Nguyen"
      },
      {
        "given": "Danielle",
        "family": "VanLeer"
      },
      {
        "given": "Paul",
        "family": "Shinn"
      },
      {
        "given": "Ajit",
        "family": "Jadhav"
      },
      {
        "given": "Rolf",
        "family": "Müller"
      },
      {
        "given": "Katrina M",
        "family": "Waters"
      },
      {
        "given": "Wenyuan",
        "family": "Shi"
      },
      {
        "given": "Xueting",
        "family": "Liu"
      },
      {
        "given": "Lixin",
        "family": "Zhang"
      },
      {
        "given": "Rob",
        "family": "Knight"
      },
      {
        "given": "Paul R",
        "family": "Jensen"
      },
      {
        "given": "Bernhard Ø",
        "family": "Palsson"
      },
      {
        "given": "Kit",
        "family": "Pogliano"
      },
      {
        "given": "Roger G",
        "family": "Linington"
      },
      {
        "given": "Marcelino",
        "family": "Gutiérrez"
      },
      {
        "given": "Norberto P",
        "family": "Lopes"
      },
      {
        "given": "William H",
        "family": "Gerwick"
      },
      {
        "given": "Bradley S",
        "family": "Moore"
      },
      {
        "given": "Pieter C",
        "family": "Dorrestein"
      },
      {
        "given": "Nuno",
        "family": "Bandeira"
      }
    ],
    "container-title": "Nature Biotechnology",
    "language": "en",
    "issued": {
      "date-parts": [
        [
          2016,
          8
        ]
      ]
    },
    "URL": "https://doi.org/f8zxbs",
    "container-title-short": "Nat Biotechnol",
    "PMCID": "PMC5321674",
    "PMID": "27504778",
    "id": "dradflfa",
    "note": "This CSL Item was generated by Manubot v0.5.2 from its persistent identifier (standard_id).\nstandard_id: doi:10.1038/nbt.3597"
  },
  {
    "publisher": "Springer Science and Business Media LLC",
    "DOI": "10.1038/news.2011.498",
    "type": "article-journal",
    "source": "Crossref",
    "title": "Number of species on Earth tagged at 8.7 million",
    "author": [
      {
        "given": "Lee",
        "family": "Sweetlove"
      }
    ],
    "container-title": "Nature",
    "language": "en",
    "issued": {
      "date-parts": [
        [
          2011,
          8,
          23
        ]
      ]
    },
    "URL": "https://doi.org/djwm2d",
    "container-title-short": "Nature",
    "id": "MVK3yEOU",
    "note": "This CSL Item was generated by Manubot v0.5.2 from its persistent identifier (standard_id).\nstandard_id: doi:10.1038/news.2011.498"
  },
  {
    "publisher": "American Association for the Advancement of Science (AAAS)",
    "issue": "5543",
    "abstract": "<jats:p>The ecological consequences of biodiversity loss have aroused considerable interest and controversy during the past decade. Major advances have been made in describing the relationship between species diversity and ecosystem processes, in identifying functionally important species, and in revealing underlying mechanisms. There is, however, uncertainty as to how results obtained in recent experiments scale up to landscape and regional levels and generalize across ecosystem types and processes. Larger numbers of species are probably needed to reduce temporal variability in ecosystem processes in changing environments. A major future challenge is to determine how biodiversity dynamics, ecosystem processes, and abiotic factors interact.</jats:p>",
    "DOI": "10.1126/science.1064088",
    "type": "article-journal",
    "page": "804-808",
    "source": "Crossref",
    "title": "Biodiversity and Ecosystem Functioning: Current Knowledge and Future Challenges",
    "volume": "294",
    "author": [
      {
        "given": "M.",
        "family": "Loreau"
      },
      {
        "given": "S.",
        "family": "Naeem"
      },
      {
        "given": "P.",
        "family": "Inchausti"
      },
      {
        "given": "J.",
        "family": "Bengtsson"
      },
      {
        "given": "J. P.",
        "family": "Grime"
      },
      {
        "given": "A.",
        "family": "Hector"
      },
      {
        "given": "D. U.",
        "family": "Hooper"
      },
      {
        "given": "M. A.",
        "family": "Huston"
      },
      {
        "given": "D.",
        "family": "Raffaelli"
      },
      {
        "given": "B.",
        "family": "Schmid"
      },
      {
        "given": "D.",
        "family": "Tilman"
      },
      {
        "given": "D. A.",
        "family": "Wardle"
      }
    ],
    "container-title": "Science",
    "language": "en",
    "issued": {
      "date-parts": [
        [
          2001,
          10,
          26
        ]
      ]
    },
    "URL": "https://doi.org/cnf65t",
    "container-title-short": "Science",
    "PMID": "11679658",
    "id": "NfEL5Brl",
    "note": "This CSL Item was generated by Manubot v0.5.2 from its persistent identifier (standard_id).\nstandard_id: doi:10.1126/science.1064088"
  },
  {
    "publisher": "American Association for the Advancement of Science (AAAS)",
    "issue": "6393",
    "DOI": "10.1126/science.aau0191",
    "type": "article-journal",
    "page": "1080-1081",
    "source": "Crossref",
    "title": "The misunderstood sixth mass extinction",
    "volume": "360",
    "author": [
      {
        "given": "Gerardo",
        "family": "Ceballos"
      },
      {
        "given": "Paul R.",
        "family": "Ehrlich"
      }
    ],
    "container-title": "Science",
    "language": "en",
    "editor": [
      {
        "given": "Jennifer",
        "family": "Sills"
      }
    ],
    "issued": {
      "date-parts": [
        [
          2018,
          6,
          8
        ]
      ]
    },
    "URL": "https://doi.org/ggf4kk",
    "container-title-short": "Science",
    "PMID": "29880679",
    "id": "ZKWtA8aI",
    "note": "This CSL Item was generated by Manubot v0.5.2 from its persistent identifier (standard_id).\nstandard_id: doi:10.1126/science.aau0191"
  },
  {
    "publisher": "Annual Reviews",
    "issue": "1",
    "abstract": "<jats:p> Species diversity is a major determinant of ecosystem productivity, stability, invasibility, and nutrient dynamics. Hundreds of studies spanning terrestrial, aquatic, and marine ecosystems show that high-diversity mixtures are approximately twice as productive as monocultures of the same species and that this difference increases through time. These impacts of higher diversity have multiple causes, including interspecific complementarity, greater use of limiting resources, decreased herbivory and disease, and nutrient-cycling feedbacks that increase nutrient stores and supply rates over the long term. These experimentally observed effects of diversity are consistent with predictions based on a variety of theories that share a common feature: All have trade-off-based mechanisms that allow long-term coexistence of many different competing species. Diversity loss has an effect as great as, or greater than, the effects of herbivory, fire, drought, nitrogen addition, elevated CO<jats:sub>2</jats:sub>, and other drivers of environmental change. The preservation, conservation, and restoration of biodiversity should be a high global priority. </jats:p>",
    "DOI": "10.1146/annurev-ecolsys-120213-091917",
    "type": "article-journal",
    "page": "471-493",
    "source": "Crossref",
    "title": "Biodiversity and Ecosystem Functioning",
    "volume": "45",
    "author": [
      {
        "given": "David",
        "family": "Tilman"
      },
      {
        "given": "Forest",
        "family": "Isbell"
      },
      {
        "given": "Jane M.",
        "family": "Cowles"
      }
    ],
    "container-title": "Annual Review of Ecology, Evolution, and Systematics",
    "language": "en",
    "issued": {
      "date-parts": [
        [
          2014,
          11,
          23
        ]
      ]
    },
    "URL": "https://doi.org/gf5tpq",
    "container-title-short": "Annu. Rev. Ecol. Evol. Syst.",
    "id": "aC7xojka",
    "note": "This CSL Item was generated by Manubot v0.5.2 from its persistent identifier (standard_id).\nstandard_id: doi:10.1146/annurev-ecolsys-120213-091917"
  },
  {
    "publisher": "Frontiers Media SA",
    "DOI": "10.3389/fpls.2019.01329",
    "type": "article-journal",
    "source": "Crossref",
    "title": "Taxonomically Informed Scoring Enhances Confidence in Natural Products Annotation",
    "volume": "10",
    "author": [
      {
        "given": "Adriano",
        "family": "Rutz"
      },
      {
        "given": "Miwa",
        "family": "Dounoue-Kubo"
      },
      {
        "given": "Simon",
        "family": "Ollivier"
      },
      {
        "given": "Jonathan",
        "family": "Bisson"
      },
      {
        "given": "Mohsen",
        "family": "Bagheri"
      },
      {
        "given": "Tongchai",
        "family": "Saesong"
      },
      {
        "given": "Samad Nejad",
        "family": "Ebrahimi"
      },
      {
        "given": "Kornkanok",
        "family": "Ingkaninan"
      },
      {
        "given": "Jean-Luc",
        "family": "Wolfender"
      },
      {
        "given": "Pierre-Marie",
        "family": "Allard"
      }
    ],
    "container-title": "Frontiers in Plant Science",
    "issued": {
      "date-parts": [
        [
          2019,
          10,
          25
        ]
      ]
    },
    "URL": "https://doi.org/fm73",
    "container-title-short": "Front. Plant Sci.",
    "PMCID": "PMC6824209",
    "PMID": "31708947",
    "id": "1EaGvQl0B",
    "note": "This CSL Item was generated by Manubot v0.5.2 from its persistent identifier (standard_id).\nstandard_id: doi:10.3389/fpls.2019.01329"
  },
  {
    "type": "report",
    "id": "2gMvO97S",
    "categories": [
      "Global Assessment",
      "IPBES",
      "Full assessment report"
    ],
    "language": "en",
    "author": [
      {
        "literal": "IPBES"
      }
    ],
    "issued": {
      "date-parts": [
        [
          2019,
          5,
          4
        ]
      ]
    },
    "abstract": "IPBES is to perform regular and timely assessments of knowledge on biodiversity and ecosystem services and their interlinkages at the global level. Also addressing an invitation by the Conference of the Parties of the Convention on Biological Diversity (CBD) to prepare a global assessment of biodiversity and ecosystem services building, inter alia, on its own and other relevant regional, subregional and thematic assessments, as well as on national reports. The overall scope of the assessment is to assess the status and trends with regard to biodiversity and ecosystem services, the impact of biodiversity and ecosystem services on human well-being and the effectiveness of responses, including the Strategic Plan and its Aichi Biodiversity Targets. It is anticipated that this deliverable will contribute to the process for the evaluation and renewal of the Strategic Plan for Biodiversity and its Aichi Biodiversity Targets. The IPBES Global Assessment on Biodiversity and Ecosystem Services is composed of 1) a Summary for Policymakers (SPM), approved by the IPBES Plenary at its 7th session in May 2019 in Paris, France (IPBES-7); and 2) a set of six Chapters, accepted by the IPBES Plenary.",
    "DOI": "10.5281/zenodo.6417333",
    "publisher": "Zenodo",
    "title": "Global assessment report on biodiversity and ecosystem services of the Intergovernmental Science-Policy Platform on Biodiversity and Ecosystem Services",
    "URL": "https://doi.org/grbxsr",
    "version": "1",
    "note": "This CSL Item was generated by Manubot v0.5.2 from its persistent identifier (standard_id).\nstandard_id: doi:10.5281/zenodo.6417333"
  },
  {
    "publisher": "eLife Sciences Publications, Ltd",
    "abstract": "<jats:p>Contemporary bioinformatic and chemoinformatic capabilities hold promise to reshape knowledge management, analysis and interpretation of data in natural products research. Currently, reliance on a disparate set of non-standardized, insular, and specialized databases presents a series of challenges for data access, both within the discipline and for integration and interoperability between related fields. The fundamental elements of exchange are referenced structure-organism pairs that establish relationships between distinct molecular structures and the living organisms from which they were identified. Consolidating and sharing such information via an open platform has strong transformative potential for natural products research and beyond. This is the ultimate goal of the newly established LOTUS initiative, which has now completed the first steps toward the harmonization, curation, validation and open dissemination of 750,000+ referenced structure-organism pairs. LOTUS data is hosted on Wikidata and regularly mirrored on <jats:ext-link ext-link-type=\"uri\" xlink:href=\"https://lotus.naturalproducts.net\">https://lotus.naturalproducts.net</jats:ext-link>. Data sharing within the Wikidata framework broadens data access and interoperability, opening new possibilities for community curation and evolving publication models. Furthermore, embedding LOTUS data into the vast Wikidata knowledge graph will facilitate new biological and chemical insights. The LOTUS initiative represents an important advancement in the design and deployment of a comprehensive and collaborative natural products knowledge base.</jats:p>",
    "DOI": "10.7554/elife.70780",
    "type": "article-journal",
    "source": "Crossref",
    "title": "The LOTUS initiative for open knowledge management in natural products research",
    "volume": "11",
    "author": [
      {
        "given": "Adriano",
        "family": "Rutz"
      },
      {
        "given": "Maria",
        "family": "Sorokina"
      },
      {
        "given": "Jakub",
        "family": "Galgonek"
      },
      {
        "given": "Daniel",
        "family": "Mietchen"
      },
      {
        "given": "Egon",
        "family": "Willighagen"
      },
      {
        "given": "Arnaud",
        "family": "Gaudry"
      },
      {
        "given": "James G",
        "family": "Graham"
      },
      {
        "given": "Ralf",
        "family": "Stephan"
      },
      {
        "given": "Roderic",
        "family": "Page"
      },
      {
        "given": "Jiří",
        "family": "Vondrášek"
      },
      {
        "given": "Christoph",
        "family": "Steinbeck"
      },
      {
        "given": "Guido F",
        "family": "Pauli"
      },
      {
        "given": "Jean-Luc",
        "family": "Wolfender"
      },
      {
        "given": "Jonathan",
        "family": "Bisson"
      },
      {
        "given": "Pierre-Marie",
        "family": "Allard"
      }
    ],
    "container-title": "eLife",
    "language": "en",
    "issued": {
      "date-parts": [
        [
          2022,
          5,
          26
        ]
      ]
    },
    "URL": "https://doi.org/gpzrr8",
    "PMCID": "PMC9135406",
    "PMID": "35616633",
    "id": "PYbwVCJ0",
    "note": "This CSL Item was generated by Manubot v0.5.2 from its persistent identifier (standard_id).\nstandard_id: doi:10.7554/elife.70780"
  }
]
